[
    {
        "name":"Digicel",
        "last_scrape":"",
        "home_url":"",
        "start":{
            "base_url":"https://careers.digicelgroup.com",
            "url":"https://careers.digicelgroup.com/search/?q=&locationsearch=Jamaica&sortColumn=sort_title&sortDirection=desc#hdrTitle",
            "selector":".jobTitle-link"
        },
        "scrape":[
            {
                "type":"title",
                "ref":"#job-title",
                "value":"string"
            },
            {
                "type":"Location",
                "ref":".jobGeoLocation",
                "value":"string"
            },
            {
                "type":"Description",
                "ref":".jobdescription",
                "value":"string"
            },
            {
                "type":"Responsibilities",
                "ref":".outershell > .jobDisplay > .jobdescription > ul > li",
                "value":"object"
            },
            {
                "type":"Name",
                "ref":"job-details--company",
                "value":"string"
            }
        ]
    },
    {
        "name":"Caribbean Jobs",
        "last_scrape":"",
        "home_url":"",
        "start":{
            "base_url":"https://careers.digicelgroup.com",
            "url":"https://www.caribbeanjobs.com/ShowResults.aspx?Keywords=&autosuggestEndpoint=%2Fautosuggest&Location=123&Category=&Recruiter=Company&Recruiter=Agency",
            "selector":".show-more"
        },
        "scrape":[
            {
                "type":"title",
                "ref":".job-details--title",
                "value":"string"
            },
            {
                "type":"Location",
                "ref":".location",
                "value":"string"
            },
            {
                "type":"Description",
                "ref":".jobdescription",
                "value":"string"
            },
            {
                "type":"Responsibilities",
                "ref":".outershell > .jobDisplay > .jobdescription > ul > li",
                "value":"object"
            },
            {
                "type":"Name",
                "ref":"job-details--company",
                "value":"string"
            }
        ]
    }
]